README.rst
setup.py
django_kvideos.egg-info/PKG-INFO
django_kvideos.egg-info/SOURCES.txt
django_kvideos.egg-info/dependency_links.txt
django_kvideos.egg-info/requires.txt
django_kvideos.egg-info/top_level.txt
kvideos/__init__.py
kvideos/models.py
kvideos/settings.py
kvideos/templatetags/__init__.py
kvideos/templatetags/kvideos.py
testing/__init__.py
testing/models.py
testing/settings.py
testing/tests.py
testing/urls.py